feynml/__init__.py
feynml/connector.py
feynml/feynmandiagram.py
feynml/feynml.py
feynml/head.py
feynml/id.py
feynml/labeled.py
feynml/leg.py
feynml/line.py
feynml/link.py
feynml/log.py
feynml/meta.py
feynml/momentum.py
feynml/particle.py
feynml/particles.py
feynml/pdgid.py
feynml/point.py
feynml/propagator.py
feynml/shape.py
feynml/sheet.py
feynml/sourcing.py
feynml/styled.py
feynml/targeting.py
feynml/type.py
feynml/util.py
feynml/vertex.py
feynml/xml.py
feynml/interface/__init__.py
feynml/interface/hepmc.py
feynml/interface/interface.py
feynml/interface/lhe.py
feynml/interface/qgraf.py
feynml/interface/formcalc/__init__.py
feynml/interface/formcalc/fermion.py
feynml/interface/formcalc/feynmangraph.py
feynml/interface/formcalc/field.py
feynml/interface/formcalc/insertions.py
feynml/interface/formcalc/particle.py
feynml/interface/formcalc/propagator.py
feynml/interface/formcalc/rule.py
feynml/interface/formcalc/sequenceform.py
feynml/interface/formcalc/topology.py
feynml/interface/formcalc/topologylist.py
feynml/interface/formcalc/vector.py
feynml/interface/formcalc/vertex.py
feynml/interface/madgraph/ps.py
feynml/interface/madgraph/plugin/__init__.py
feynml/interface/madgraph/plugin/exporter.py
feynml/topology/__init__.py
feynml/topology/four.py
feynml/topology/three.py
feynml/topology/two.py
feynml-0.3.2.dist-info/METADATA
feynml-0.3.2.dist-info/WHEEL
feynml-0.3.2.dist-info/licenses/AUTHORS
feynml-0.3.2.dist-info/licenses/LICENSE
feynml-0.3.2.dist-info/RECORD
