Metadata-Version: 2.4
Name: feynml
Version: 0.3.2
Summary: Feynman diagram markup language
Project-URL: Documentation, https://github.com/APN-Pucky/feynml#readme
Project-URL: Issues, https://github.com/APN-Pucky/feynml/issues
Project-URL: Source, https://github.com/APN-Pucky/feynml/
Author-email: Alexander Puck Neuwirth <alexander@neuwirth-informatik.de>
License-File: AUTHORS
License-File: LICENSE
Classifier: Development Status :: 4 - Beta
Classifier: Intended Audience :: Developers
Classifier: Intended Audience :: Science/Research
Classifier: License :: OSI Approved :: BSD License
Classifier: Programming Language :: Python
Classifier: Programming Language :: Python :: 3.8
Classifier: Programming Language :: Python :: 3.9
Classifier: Programming Language :: Python :: 3.10
Classifier: Programming Language :: Python :: 3.11
Classifier: Programming Language :: Python :: 3.12
Classifier: Programming Language :: Python :: 3.13
Classifier: Programming Language :: Python :: Implementation :: CPython
Classifier: Programming Language :: Python :: Implementation :: PyPy
Classifier: Topic :: Scientific/Engineering
Requires-Python: >=3.8
Requires-Dist: cssselect
Requires-Dist: cssutils>=2.10.2
Requires-Dist: deprecated
Requires-Dist: deprecation
Requires-Dist: feynmodel
Requires-Dist: networkx
Requires-Dist: particle
Requires-Dist: smpl-doc>=1.1.3
Requires-Dist: smpl-io>=1.1.2
Requires-Dist: smpl-util>=1.0.0
Requires-Dist: xsdata[cli,lxml,soap]
Provides-Extra: dev
Requires-Dist: ipython; extra == 'dev'
Requires-Dist: jupyter; extra == 'dev'
Requires-Dist: jupyterlab; extra == 'dev'
Requires-Dist: pre-commit; extra == 'dev'
Provides-Extra: docs
Requires-Dist: sphinx; extra == 'docs'
Provides-Extra: interfaces
Requires-Dist: pyhepmc; extra == 'interfaces'
Requires-Dist: pylhe; extra == 'interfaces'
Requires-Dist: pyqgraf>=0.0.3; extra == 'interfaces'
Provides-Extra: lint
Requires-Dist: ruff; extra == 'lint'
Provides-Extra: test
Requires-Dist: pyhepmc; extra == 'test'
Requires-Dist: pylhe; extra == 'test'
Requires-Dist: pyqgraf>=0.0.3; extra == 'test'
Requires-Dist: pytest; extra == 'test'
